wagtail_qrcode/__init__.py
wagtail_qrcode/admin_forms.py
wagtail_qrcode/apps.py
wagtail_qrcode/cls.py
wagtail_qrcode/field_panels.py
wagtail_qrcode/models.py
wagtail_qrcode/urls.py
wagtail_qrcode/views.py
wagtail_qrcode/wagtail_hooks.py
wagtail_qrcode/templates/wagtail_qrcode/admin/field.html
wagtail_qrcode/templates/wagtail_qrcode/admin/field_4.html
wagtail_qrcode/templates/wagtail_qrcode/admin/field_panel.html
wagtail_qrcode/templates/wagtail_qrcode/admin/field_panel_4.html
wagtail_qrcode/templates/wagtail_qrcode/admin/usage_field.html
wagtail_qrcode/templates/wagtail_qrcode/admin/usage_field_4.html
wagtail_qrcode/templates/wagtail_qrcode/admin/usage_field_panel.html
wagtail_qrcode/templates/wagtail_qrcode/admin/usage_field_panel_4.html
wagtail_qrcode-2.1.1.dist-info/licenses/LICENSE
wagtail_qrcode-2.1.1.dist-info/METADATA
wagtail_qrcode-2.1.1.dist-info/WHEEL
wagtail_qrcode-2.1.1.dist-info/top_level.txt
wagtail_qrcode-2.1.1.dist-info/RECORD
