Metadata-Version: 2.4
Name: wagtail-qrcode
Version: 2.1.1
Summary: Create a QR code that can be used to link to a wagtail page
Author-email: Nick Moreton <nickmoreton@me.com>
License: 
Project-URL: Repository, https://github.com/wagtail-packages/wagtail-qrcode
Project-URL: Issues, https://github.com/wagtail-packages/wagtail-qrcode/issues
Project-URL: Changelog, https://github.com/wagtail-packages/wagtail-qrcode/blob/release/CHANGELOG.md
Keywords: wagtail,qrcode
Classifier: Development Status :: 5 - Production/Stable
Classifier: Intended Audience :: Developers
Classifier: License :: OSI Approved :: MIT License
Classifier: Operating System :: OS Independent
Classifier: Programming Language :: Python
Classifier: Programming Language :: Python :: 3
Classifier: Programming Language :: Python :: 3.9
Classifier: Programming Language :: Python :: 3.10
Classifier: Programming Language :: Python :: 3.11
Classifier: Programming Language :: Python :: 3.12
Classifier: Programming Language :: Python :: 3.13
Classifier: Framework :: Django
Classifier: Framework :: Django :: 4.2
Classifier: Framework :: Django :: 5.0
Classifier: Framework :: Django :: 5.1
Classifier: Framework :: Wagtail
Classifier: Framework :: Wagtail :: 5
Classifier: Framework :: Wagtail :: 6
Requires-Python: >=3.9
License-File: LICENSE
Requires-Dist: Wagtail>=5.2
Requires-Dist: PyQRCode<2,>=1
Provides-Extra: development
Requires-Dist: black==24.10.0; extra == "development"
Requires-Dist: flake8==7.1.1; extra == "development"
Requires-Dist: isort==5.13.2; extra == "development"
Provides-Extra: testing
Requires-Dist: coverage; extra == "testing"
Dynamic: license-file
